promptshell/__init__.py
promptshell/ai_terminal_assistant.py
promptshell/ansi_support.py
promptshell/data_gatherer.py
promptshell/format_utils.py
promptshell/main.py
promptshell/node.py
promptshell/readline_setup.py
promptshell/setup.py
promptshell/system_info.py
promptshell-0.1.1.dist-info/LICENSE
promptshell-0.1.1.dist-info/METADATA
promptshell-0.1.1.dist-info/WHEEL
promptshell-0.1.1.dist-info/entry_points.txt
promptshell-0.1.1.dist-info/top_level.txt
promptshell-0.1.1.dist-info/RECORD
